smemhack/__init__.py
smemhack/main.py
smemhack/images/exercise.PNG
smemhack/images/exit.PNG
smemhack/images/next.PNG
smemhack/images/question.PNG
smemhack-5.11.18.dist-info/LICENSE.txt
smemhack-5.11.18.dist-info/METADATA
smemhack-5.11.18.dist-info/WHEEL
smemhack-5.11.18.dist-info/top_level.txt
smemhack-5.11.18.dist-info/RECORD
