Metadata-Version: 2.1
Name: smemhack
Version: 5.11.18
Summary: A Python library to automate online homework tasks with AI and system control.
Home-page: UNKNOWN
Author: Dickily
Author-email: dickilyyiu@gmail.com
License: Proprietary
Platform: UNKNOWN
Classifier: License :: Other/Proprietary License
Classifier: Programming Language :: Python :: 3
Classifier: Programming Language :: Python :: 3.8
Classifier: Operating System :: OS Independent
Requires-Python: >=3.8.18
Requires-Dist: tensorflow>=2.8.0
Requires-Dist: pyautogui>=0.9.53
Requires-Dist: pyperclip>=1.8.2
Requires-Dist: numpy>=1.20.0
Requires-Dist: keyboard>=0.13.5
Requires-Dist: fuzzywuzzy>=0.18.0
Requires-Dist: python-Levenshtein>=0.12.2
Requires-Dist: Pillow>=8.0.0
